CHANGELOG.rst
LICENSE
MANIFEST.in
NOTICE
README.rst
pytest.ini
requirements.txt
setup.py
hiq_projectq.egg-info/PKG-INFO
hiq_projectq.egg-info/SOURCES.txt
hiq_projectq.egg-info/dependency_links.txt
hiq_projectq.egg-info/not-zip-safe
hiq_projectq.egg-info/requires.txt
hiq_projectq.egg-info/top_level.txt
projectq/__init__.py
projectq/_version.py
projectq/backends/__init__.py
projectq/backends/_json_converter.py
projectq/backends/_parametric_backend.py
projectq/backends/_printer.py
projectq/backends/_resource.py
projectq/backends/_aqt/__init__.py
projectq/backends/_aqt/_aqt.py
projectq/backends/_aqt/_aqt_http_client.py
projectq/backends/_circuits/__init__.py
projectq/backends/_circuits/_drawer.py
projectq/backends/_circuits/_drawer_matplotlib.py
projectq/backends/_circuits/_plot.py
projectq/backends/_circuits/_to_latex.py
projectq/backends/_ibm/__init__.py
projectq/backends/_ibm/_ibm.py
projectq/backends/_ibm/_ibm_http_client.py
projectq/backends/_sim/__init__.py
projectq/backends/_sim/_classical_simulator.py
projectq/backends/_sim/_cppsim.cpp
projectq/backends/_sim/_pysim.py
projectq/backends/_sim/_simulator.py
projectq/backends/_sim/_cppkernels/fusion.hpp
projectq/backends/_sim/_cppkernels/simulator.hpp
projectq/backends/_sim/_cppkernels/intrin/alignedallocator.hpp
projectq/backends/_sim/_cppkernels/intrin/cintrin.hpp
projectq/backends/_sim/_cppkernels/intrin/kernel1.hpp
projectq/backends/_sim/_cppkernels/intrin/kernel2.hpp
projectq/backends/_sim/_cppkernels/intrin/kernel3.hpp
projectq/backends/_sim/_cppkernels/intrin/kernel4.hpp
projectq/backends/_sim/_cppkernels/intrin/kernel5.hpp
projectq/backends/_sim/_cppkernels/intrin/kernels.hpp
projectq/backends/_sim/_cppkernels/nointrin/kernel1.hpp
projectq/backends/_sim/_cppkernels/nointrin/kernel2.hpp
projectq/backends/_sim/_cppkernels/nointrin/kernel3.hpp
projectq/backends/_sim/_cppkernels/nointrin/kernel4.hpp
projectq/backends/_sim/_cppkernels/nointrin/kernel5.hpp
projectq/backends/_sim/_cppkernels/nointrin/kernels.hpp
projectq/cengines/__init__.py
projectq/cengines/_ibm5qubitmapper.py
projectq/cengines/_linearmapper.py
projectq/cengines/_manualmapper.py
projectq/cengines/_optimize.py
projectq/cengines/_swapandcnotflipper.py
