Metadata-Version: 1.2
Name: hiq-projectq
Version: 0.6.4
Summary: ProjectQ - An open source software framework for quantum computing
Home-page: http://www.projectq.ch
Author: Huawei-HiQ
Author-email: hiqinfo@huawei.com
License: Apache 2
Project-URL: Documentation, https://hiq-projectq.readthedocs.io/en/latest/
Project-URL: Issue Tracker, https://github.com/Huawei-HiQ/ProjectQ/
Platform: UNKNOWN
Requires-Python: >=3.5
